{
"account_id": "myaccount_id",
"role_name": "myrole_name",
"region": "my_region_name",
"action": "stauts",
"resources": {
    "ec2": [
        { "ec2": "myec2-01" },
        { "ec2": "myec2-02" },
        { "ec2": "myec2-03" },
        { "ec2": "myec2-04" }
    ],
    "rds": [
        { "id": "aurora-sql" },
        { "id": "aurora-sql" },
        { "id": "aurora-sql" }
    ],
    "docdb": [
        { "id": "aurora-sql" },
        { "id": "aurora-sql" },
        { "id": "aurora-sql" }
    ]
    }
}
